bmail/__init__.py
bmail/text_mailer.py
bmail/emails_test/__init__.py
bmail/emails_test/emails_test.py
bmail-0.4.0.dist-info/METADATA
bmail-0.4.0.dist-info/RECORD
bmail-0.4.0.dist-info/WHEEL
bmail-0.4.0.dist-info/top_level.txt
