Metadata-Version: 2.1
Name: bmail
Version: 0.4.0
Summary: Email library
Home-page: https://github.com/BlackEarth/bmail
Author: Sean Harrison
Author-email: sah@blackearthgroup.com
License: LGPL 3.0
Platform: UNKNOWN
Classifier: Development Status :: 3 - Alpha
Classifier: Intended Audience :: Developers
Classifier: License :: OSI Approved :: GNU Library or Lesser General Public License (LGPL)
Classifier: Programming Language :: Python :: 3
Provides-Extra: test
Provides-Extra: dev
Requires-Dist: bl
Provides-Extra: dev
Provides-Extra: test
